breez_sdk_liquid/__init__.py
breez_sdk_liquid/breez_sdk_liquid.py
breez_sdk_liquid/libbreez_sdk_liquid_bindings.so
breez_sdk_liquid-0.11.13.dist-info/METADATA
breez_sdk_liquid-0.11.13.dist-info/WHEEL
breez_sdk_liquid-0.11.13.dist-info/top_level.txt
breez_sdk_liquid-0.11.13.dist-info/RECORD
