Metadata-Version: 2.4
Name: breez_sdk_liquid
Version: 0.11.13
Summary: Python language bindings for the Breez Liquid SDK
Home-page: https://github.com/breez/breez-sdk-liquid
Author: Breez <contact@breez.technology>
License: MIT
Dynamic: author
Dynamic: description
Dynamic: description-content-type
Dynamic: home-page
Dynamic: license
Dynamic: summary
